altitudo/__init__.py
altitudo/altitudo.py
altitudo/cli.py
altitudo-0.1.0.dist-info/DESCRIPTION.rst
altitudo-0.1.0.dist-info/METADATA
altitudo-0.1.0.dist-info/RECORD
altitudo-0.1.0.dist-info/WHEEL
altitudo-0.1.0.dist-info/entry_points.txt
altitudo-0.1.0.dist-info/metadata.json
altitudo-0.1.0.dist-info/top_level.txt
