Metadata-Version: 2.0
Name: altitudo
Version: 0.1.0
Summary: Package to get elevation / altitude from a given geo coordinate
Home-page: https://github.com/milesgranger/altitudo
Author: Miles Granger
Author-email: miles59923@gmail.com
License: The Unlicense
Keywords: altitudo,elevation,altitude
Platform: UNKNOWN
Classifier: Development Status :: 5 - Production/Stable
Classifier: Intended Audience :: Developers
Classifier: License :: OSI Approved :: MIT License
Classifier: Natural Language :: English
Classifier: Programming Language :: Python :: 2
Classifier: Programming Language :: Python :: 2.7
Classifier: Programming Language :: Python :: 3
Classifier: Programming Language :: Python :: 3.4
Classifier: Programming Language :: Python :: 3.5
Classifier: Programming Language :: Python :: 3.6
Classifier: Programming Language :: Python :: 3.7
Requires-Dist: Click (>=6.0)
Requires-Dist: requests (>=2.0)
